banterbot/__init__.py
banterbot/config.py
banterbot/paths.py
banterbot/characters/__init__.py
banterbot/characters/android.py
banterbot/characters/bartender.py
banterbot/characters/chef.py
banterbot/characters/historian.py
banterbot/characters/quiz.py
banterbot/characters/teacher_french.py
banterbot/characters/teacher_mandarin.py
banterbot/characters/therapist.py
banterbot/data/__init__.py
banterbot/data/enums.py
banterbot/data/prompts.py
banterbot/exceptions/__init__.py
banterbot/exceptions/format_mismatch_error.py
banterbot/extensions/__init__.py
banterbot/extensions/interface.py
banterbot/extensions/option_selector.py
banterbot/extensions/persona.py
banterbot/extensions/prosody_selector.py
banterbot/gui/__init__.py
banterbot/gui/cli.py
banterbot/gui/tk_interface.py
banterbot/handlers/__init__.py
banterbot/handlers/speech_recognition_handler.py
banterbot/handlers/speech_synthesis_handler.py
banterbot/handlers/stream_handler.py
banterbot/managers/__init__.py
banterbot/managers/azure_neural_voice_manager.py
banterbot/managers/memory_chain.py
banterbot/managers/openai_model_manager.py
banterbot/managers/resource_manager.py
banterbot/managers/stream_manager.py
banterbot/models/__init__.py
banterbot/models/azure_neural_voice_profile.py
banterbot/models/memory.py
banterbot/models/message.py
banterbot/models/number.py
banterbot/models/openai_model.py
banterbot/models/phrase.py
banterbot/models/speech_recognition_input.py
banterbot/models/stream_log_entry.py
banterbot/models/word.py
banterbot/models/traits/__init__.py
banterbot/models/traits/primary_trait.py
banterbot/models/traits/secondary_trait.py
banterbot/models/traits/tertiary_trait.py
banterbot/protos/__init__.py
banterbot/protos/memory_pb2.py
banterbot/resources/__init__.py
banterbot/resources/openai_models.json
banterbot/resources/primary_traits.json
banterbot/resources/traits.csv
banterbot/services/__init__.py
banterbot/services/openai_service.py
banterbot/services/speech_recognition_service.py
BanterBot-0.0.16.dist-info/METADATA
BanterBot-0.0.16.dist-info/WHEEL
BanterBot-0.0.16.dist-info/entry_points.txt
BanterBot-0.0.16.dist-info/top_level.txt
BanterBot-0.0.16.dist-info/RECORD
