Metadata-Version: 2.1
Name: BanterBot
Version: 0.0.16
Summary: BanterBot: An OpenAI ChatGPT-powered chatbot with Azure Neural Voices. Supports speech-to-text and text-to-speech interactions with emotional tone selection. Features real-time monitoring and Tkinter frontend.
Home-page: https://github.com/GabrielSCabrera/BanterBot
Download-URL: https://github.com/GabrielSCabrera/BanterBot/releases/download/v0.0.16-alpha/BanterBot-0.0.16.tar.gz
Author: Gabriel S. Cabrera
Author-email: gabriel.sigurd.cabrera@gmail.com
Keywords: tkinter,tk,gpt,gui,windows,linux,cross-platform,chatgpt,text-to-speech,speech-to-text,tts,stt,chatbot,openai,interactive
Classifier: Development Status :: 3 - Alpha
Classifier: Environment :: Console
Classifier: Intended Audience :: Developers
Classifier: Intended Audience :: End Users/Desktop
Classifier: Programming Language :: Python :: 3.9
Classifier: Programming Language :: Python :: 3.10
Classifier: Programming Language :: Python :: 3.11
Classifier: Topic :: Communications :: Chat
Classifier: Topic :: Multimedia :: Sound/Audio :: Speech
Classifier: Topic :: Scientific/Engineering :: Artificial Intelligence
Classifier: Topic :: Utilities
Requires-Python: >=3.9
Requires-Dist: azure-cognitiveservices-speech >=1.37.0
Requires-Dist: numba >=0.59.1
Requires-Dist: numpy >=1.26.2
Requires-Dist: openai >=1.23.2
Requires-Dist: protobuf ==4.25.1
Requires-Dist: requests >=2.31.0
Requires-Dist: spacy >=3.7.4
Requires-Dist: tiktoken >=0.7.0
Requires-Dist: uuid6 >=2024.1.12
